{
  "small_potion": {
    "name": "スモールポーション",
    "description": "HPを少し回復する小さなポーション。",
    "usable": true,
    "effects": [{"type": "heal", "stat": "hp", "amount": 30}]
  },
  "medium_potion": {
    "name": "ミディアムポーション",
    "description": "HPを中程度回復するポーション。",
    "usable": true,
    "effects": [{"type": "heal", "stat": "hp", "amount": 60}]
  },
  "large_potion": {
    "name": "ラージポーション",
    "description": "HPを大きく回復する高級ポーション。",
    "usable": true,
    "effects": [{"type": "heal", "stat": "hp", "amount": 120}]
  },
  "ether": {
    "name": "エーテル",
    "description": "MPを中程度回復する神秘の液体。",
    "usable": true,
    "effects": [{"type": "heal", "stat": "mp", "amount": 30}]
  },
  "antidote": {
    "name": "アンチドート",
    "description": "毒状態を治療する解毒薬。",
    "usable": true,
    "effects": [{"type": "cure_status", "status": "poison"}]
  },
  "elixir": {
    "name": "エリクサー",
    "description": "HPとMPを完全に回復する万能薬。",
    "usable": true,
    "effects": [
      {"type": "heal", "stat": "hp", "amount": "full"},
      {"type": "heal", "stat": "mp", "amount": "full"}
    ]
  },
  "revive_scroll": {
    "name": "リバイブスクロール",
    "description": "戦闘不能の味方1体を復活させる古文書。",
    "usable": true,
    "effects": [{"type": "revive", "amount": "half"}]
  },
  "magic_stone": {
    "name": "魔石",
    "description": "モンスター合成に用いられる不思議な石。合成研究所で特定の組み合わせに必須。"
  },
  "dragon_scale": {
    "name": "ドラゴンスケイル",
    "description": "若きドラゴンの鱗。強力な合成素材。"
  },
  "abyss_shard": {
    "name": "アビスシャード",
    "description": "闇の深淵で取れる黒水晶。ダークソウル系モンスターの合成に使う。"
  },
  "celestial_feather": {
    "name": "セレスティアルフェザー",
    "description": "光を宿す神鳥の羽根。高ランク合成素材。"
  },
  "thunder_core": {
    "name": "サンダーコア",
    "description": "強力な電気エネルギーを帯びた核。"
  },
  "frost_crystal": {
    "name": "フロストクリスタル",
    "description": "極寒地で採れる冷気を封じ込めた氷晶。"
  },
  "weapon_core_common": {
    "name": "下級・武器の核",
    "description": "武器強化に使われる基本的な素材。"
  },
  "weapon_core_rare": {
    "name": "上級・武器の核",
    "description": "高品質な武器強化素材。"
  },
  "armor_fragment_common": {
    "name": "下級・防具の欠片",
    "description": "防具強化に使われる基本的な素材。"
  },
  "armor_fragment_rare": {
    "name": "上級・防具の欠片",
    "description": "高品質な防具強化素材。"
  },
  "steel_ingot": {
    "name": "鋼のインゴット",
    "description": "鋼の装備品を作るための素材。"
  },
  "fire_crystal": {
    "name": "炎の結晶",
    "description": "炎属性の装備品を作るための素材。"
  },
  "tough_leather": {
    "name": "頑丈な革",
    "description": "高品質な防具を作るための素材。"
  },
  "power_fragment": {
    "name": "力の破片",
    "description": "力のアクセサリーを作るための素材。"
  }
}